gradio_yolov8_det/__init__.py
gradio_yolov8_det/gradio_yolov8_det_client.py
gradio_yolov8_det/gradio_yolov8_det_v2.py
gradio_yolov8_det/gradio_yolov8_det_v2_test.py
gradio_yolov8_det/gyd_style.css
gradio_yolov8_det/test.py
gradio_yolov8_det/cls_name/ImageNet_clasName.txt
gradio_yolov8_det/cls_name/ImageNet_clasName_zh.txt
gradio_yolov8_det/cls_name/cls_imagenet_name_zh.yaml
gradio_yolov8_det/cls_name/cls_name.csv
gradio_yolov8_det/cls_name/cls_name.yaml
gradio_yolov8_det/cls_name/cls_name_ar.yaml
gradio_yolov8_det/cls_name/cls_name_custom.yaml
gradio_yolov8_det/cls_name/cls_name_en.yaml
gradio_yolov8_det/cls_name/cls_name_es.yaml
gradio_yolov8_det/cls_name/cls_name_ko.yaml
gradio_yolov8_det/cls_name/cls_name_ru.yaml
gradio_yolov8_det/cls_name/cls_name_zh.yaml
gradio_yolov8_det/gyd_utils/__init__.py
gradio_yolov8_det/gyd_utils/fonts_opt.py
gradio_yolov8_det/icon/logo.ico
"gradio_yolov8_det/img_examples/1024px-Motorcyclists_lane_splitting_in_Bangkok,_Thailand.jpg"
gradio_yolov8_det/img_examples/MichaelMiley.jpg
gradio_yolov8_det/img_examples/Millenial-at-work.jpg
gradio_yolov8_det/img_examples/bus.jpg
gradio_yolov8_det/img_examples/giraffe.jpg
gradio_yolov8_det/img_examples/zidane.jpg
gradio_yolov8_det/img_examples/img_clas/ILSVRC2012_val_00000008.JPEG
gradio_yolov8_det/img_examples/img_clas/ILSVRC2012_val_00000018.JPEG
gradio_yolov8_det/img_examples/img_clas/ILSVRC2012_val_00000023.JPEG
gradio_yolov8_det/img_examples/img_clas/ILSVRC2012_val_00000067.JPEG
gradio_yolov8_det/img_examples/img_clas/ILSVRC2012_val_00000077.JPEG
gradio_yolov8_det/img_examples/img_clas/ILSVRC2012_val_00000247.JPEG
gradio_yolov8_det/model_config/model_name_all.csv
gradio_yolov8_det/model_config/model_name_all.yaml
gradio_yolov8_det/model_config/model_name_custom.yaml
gradio_yolov8_det-2.1.0.dist-info/LICENSE
gradio_yolov8_det-2.1.0.dist-info/METADATA
gradio_yolov8_det-2.1.0.dist-info/WHEEL
gradio_yolov8_det-2.1.0.dist-info/entry_points.txt
gradio_yolov8_det-2.1.0.dist-info/top_level.txt
gradio_yolov8_det-2.1.0.dist-info/RECORD
