Metadata-Version: 2.1
Name: gradio-yolov8-det
Version: 2.1.0
Summary: 基于 Gradio 的 YOLOv8 通用计算机视觉演示系统
Author: 曾逸夫 Zeng Yifu
Maintainer: 曾逸夫 Zeng Yifu
License: GPL-3.0
Project-URL: Bug Reports, https://gitee.com/CV_Lab/gradio-yolov8-det/issues
Project-URL: Funding, https://gitee.com/CV_Lab
Project-URL: Source, https://gitee.com/CV_Lab/gradio-yolov8-det
Keywords: YOLOv8,Gradio,目标检测,图像分割,图像分类
Requires-Python: >=3.8
License-File: LICENSE
Requires-Dist: click >=8.1
Requires-Dist: ultralytics >=8.1.1
Requires-Dist: gradio >=4.14.0
Requires-Dist: gradio-imageslider
Requires-Dist: opencv-python >=4.9.0.80
Requires-Dist: matplotlib
Requires-Dist: numpy >=1.24.4
Requires-Dist: pandas
Requires-Dist: pyyaml
Requires-Dist: pillow >=10.1.0
Requires-Dist: wget >=3.2
Requires-Dist: rich >=12.2.0
Requires-Dist: black
Requires-Dist: mdformat
Requires-Dist: build
Requires-Dist: twine
